[
  {
    "strategy": "A · Naive RAG",
    "faithfulness": 0.718,
    "context_precision": 1.000,
    "answer_relevance": 0.549,
    "correctness": 0.483,
    "pct_correct": 40.0,
    "latency_ms": 9669
  },
  {
    "strategy": "B · Semantic RAG",
    "faithfulness": 0.716,
    "context_precision": 1.000,
    "answer_relevance": 0.556,
    "correctness": 0.504,
    "pct_correct": 50.0,
    "latency_ms": 9525
  },
  {
    "strategy": "C · Hybrid RAG",
    "faithfulness": 0.811,
    "context_precision": 0.876,
    "answer_relevance": 0.525,
    "correctness": 0.515,
    "pct_correct": 56.0,
    "latency_ms": 11494
  },
  {
    "strategy": "D · Hybrid + Reranker",
    "faithfulness": 0.833,
    "context_precision": 0.888,
    "answer_relevance": 0.530,
    "correctness": 0.527,
    "pct_correct": 64.0,
    "latency_ms": 12047
  },
  {
    "strategy": "Adaptive Router",
    "faithfulness": 0.785,
    "context_precision": 0.892,
    "answer_relevance": 0.509,
    "correctness": 0.504,
    "pct_correct": 60.0,
    "latency_ms": 11133
  }
]
